CHANGELOG.md
requirements_extractor/__init__.py
requirements_extractor/__main__.py
requirements_extractor/__version__.py
requirements_extractor/extractor.py
requirements_extractor/gitlab_connector.py
requirements_extractor/gitlab_models.py
gitlab_requirements_extractor-0.1.0.dist-info/entry_points.txt
gitlab_requirements_extractor-0.1.0.dist-info/WHEEL
gitlab_requirements_extractor-0.1.0.dist-info/METADATA
gitlab_requirements_extractor-0.1.0.dist-info/RECORD
